{"897-677": [{"c": 497, "nv0": 0.291, "nv1": -0.503}, {"c": 161, "nv0": 0.76, "nv1": 0.115}, {"c": 256, "nv0": 0.358, "nv1": -0.256}, "...", {"c": 41, "nv0": -0.154, "nv1": 0.845}, {"c": 100, "nv0": -0.019, "nv1": 0.983}, {"c": 99, "nv0": 0.362, "nv1": 1.637}], "308-990": [{"c": 81, "nv0": 0.931, "nv1": 0.04}, {"c": 38, "nv0": 0.943, "nv1": 0.124}, {"c": 88, "nv0": 1.407, "nv1": 0.663}, "...", {"c": 270, "nv0": 0.03, "nv1": 0.706}, {"c": 497, "nv0": -0.542, "nv1": 0.214}, {"c": 55, "nv0": -0.378, "nv1": 0.427}], "897-990": [{"c": 489, "nv0": 0.109, "nv1": -0.335}, {"c": 348, "nv0": 0.197, "nv1": -0.227}, {"c": 469, "nv0": 1.337, "nv1": 0.914}, "...", {"c": 69, "nv0": -0.031, "nv1": 0.476}, {"c": 105, "nv0": -0.293, "nv1": 0.311}, {"c": 100, "nv0": -0.019, "nv1": 1.182}], "308-897": [{"c": 81, "nv0": 0.931, "nv1": -0.246}, {"c": 99, "nv0": 1.528, "nv1": 0.362}, {"c": 24, "nv0": 1.392, "nv1": 0.331}, "...", {"c": 450, "nv0": 0.039, "nv1": 0.745}, {"c": 497, "nv0": -0.542, "nv1": 0.291}, {"c": 256, "nv0": -0.719, "nv1": 0.358}], "712-677": [{"c": 23, "nv0": 0.878, "nv1": 0.008}, {"c": 52, "nv0": 0.398, "nv1": -0.403}, {"c": 33, "nv0": 0.386, "nv1": -0.276}, "...", {"c": 443, "nv0": -0.722, "nv1": 0.424}, {"c": 100, "nv0": -0.542, "nv1": 0.983}, {"c": 62, "nv0": -0.82, "nv1": 0.969}], "308-677": [{"c": 20, "nv0": 0.652, "nv1": 0.08}, {"c": 69, "nv0": 0.887, "nv1": 0.426}, {"c": 59, "nv0": 0.393, "nv1": -0.023}, "...", {"c": 62, "nv0": 0.352, "nv1": 0.969}, {"c": 0, "nv0": 0.377, "nv1": 1.026}, {"c": 374, "nv0": 0.763, "nv1": 1.615}], "308-712": [{"c": 100, "nv0": 0.708, "nv1": -0.542}, {"c": 62, "nv0": 0.352, "nv1": -0.82}, {"c": 443, "nv0": 0.447, "nv1": -0.722}, "...", {"c": 33, "nv0": -0.301, "nv1": 0.386}, {"c": 516, "nv0": -1.007, "nv1": -0.217}, {"c": 52, "nv0": -0.512, "nv1": 0.398}], "677-990": [{"c": 99, "nv0": 1.637, "nv1": 0.806}, {"c": 41, "nv0": 0.845, "nv1": 0.092}, {"c": 469, "nv0": 1.573, "nv1": 0.914}, "...", {"c": 492, "nv0": -0.4, "nv1": -0.028}, {"c": 105, "nv0": -0.131, "nv1": 0.311}, {"c": 497, "nv0": -0.503, "nv1": 0.214}], "max": 1.637, "677-677": [{"c": 0, "nv0": 1.026, "nv1": 1.026}, {"c": 360, "nv0": 0.073, "nv1": 0.073}, {"c": 359, "nv0": -0.095, "nv1": -0.095}, "...", {"c": 359, "nv0": -0.095, "nv1": -0.095}, {"c": 360, "nv0": 0.073, "nv1": 0.073}, {"c": 0, "nv0": 1.026, "nv1": 1.026}], "990-677": [{"c": 497, "nv0": 0.214, "nv1": -0.503}, {"c": 105, "nv0": 0.311, "nv1": -0.131}, {"c": 492, "nv0": -0.028, "nv1": -0.4}, "...", {"c": 469, "nv0": 0.914, "nv1": 1.573}, {"c": 41, "nv0": 0.092, "nv1": 0.845}, {"c": 99, "nv0": 0.806, "nv1": 1.637}], "677-897": [{"c": 99, "nv0": 1.637, "nv1": 0.362}, {"c": 100, "nv0": 0.983, "nv1": -0.019}, {"c": 41, "nv0": 0.845, "nv1": -0.154}, "...", {"c": 256, "nv0": -0.256, "nv1": 0.358}, {"c": 161, "nv0": 0.115, "nv1": 0.76}, {"c": 497, "nv0": -0.503, "nv1": 0.291}], "712-897": [{"c": 23, "nv0": 0.878, "nv1": 0.008}, {"c": 99, "nv0": 1.209, "nv1": 0.362}, {"c": 263, "nv0": 0.385, "nv1": -0.356}, "...", {"c": 270, "nv0": -0.51, "nv1": 0.418}, {"c": 161, "nv0": -0.172, "nv1": 0.76}, {"c": 62, "nv0": -0.82, "nv1": 0.644}], "classes": [677, 897, 308, 712, 990, 677], "712-990": [{"c": 23, "nv0": 0.878, "nv1": -0.15}, {"c": 507, "nv0": 0.47, "nv1": -0.332}, {"c": 93, "nv0": 1.057, "nv1": 0.369}, "...", {"c": 270, "nv0": -0.51, "nv1": 0.706}, {"c": 62, "nv0": -0.82, "nv1": 0.507}, {"c": 100, "nv0": -0.542, "nv1": 1.182}], "channels": [20, 69, 59, 23, 361, 56, 181, 60, 49, 38, 374, 0, 62, 469, 257, 55, 256, 270, 322, 250, 100, 443, 81, 88, 24, 52, 516, 33, 263, 507, 489, 99, 41, 210, 497, 450, 161, 71, 298, 2, 93, 105, 515, 485, 17, 404, 520, 248, 461, 14, 280, 505, 306, 112, 492, 419, 170, 424, 284, 123, 490, 360, 359, 358, 357, 356, 355, 354, 353, 352, 360, 359, 358, 357, 356, 355, 354, 353, 352, 271, 67, 21, 525, 225, 348, 286, 37], "677-712": [{"c": 62, "nv0": 0.969, "nv1": -0.82}, {"c": 100, "nv0": 0.983, "nv1": -0.542}, {"c": 443, "nv0": 0.424, "nv1": -0.722}, "...", {"c": 33, "nv0": -0.276, "nv1": 0.386}, {"c": 52, "nv0": -0.403, "nv1": 0.398}, {"c": 23, "nv0": 0.008, "nv1": 0.878}]}